<?xml version="1.0" encoding="utf-8"?>
<doctrine-mapping xmlns="http://doctrine-project.org/schemas/orm/doctrine-mapping" xmlns:xsi="http://www.w3.org/2001/XMLSchema-instance" xsi:schemaLocation="http://doctrine-project.org/schemas/orm/doctrine-mapping http://doctrine-project.org/schemas/orm/doctrine-mapping.xsd">
  <entity name="AppBundle\Entity\Archivierungen" table="Archivierungen">
    <indexes>
      <index name="FK_Studiengang_ID" columns="Studiengang_ID"/>
      <index name="FK_Fachbereich_ID" columns="Fachbereich_ID"/>
      <index name="FK_Benutzer_ID" columns="Benutzer_ID"/>
      <index name="FK_Archiv_Kategorie_ID" columns="Archiv_Kategorie_ID"/>
    </indexes>
    <id name="archivId" type="integer" column="Archiv_ID">
      <generator strategy="IDENTITY"/>
    </id>
    <field name="studiengangId" type="integer" column="Studiengang_ID" nullable="false">
      <options>
        <option name="unsigned"/>
      </options>
    </field>
    <field name="fachbereichId" type="integer" column="Fachbereich_ID" nullable="false">
      <options>
        <option name="unsigned"/>
      </options>
    </field>
    <field name="benutzerId" type="integer" column="Benutzer_ID" nullable="false">
      <options>
        <option name="unsigned"/>
      </options>
    </field>
    <field name="archivKategorieId" type="integer" column="Archiv_Kategorie_ID" nullable="false">
      <options>
        <option name="unsigned"/>
      </options>
    </field>
    <field name="titel" type="string" column="Titel" length="255" nullable="false">
      <options>
        <option name="fixed"/>
      </options>
    </field>
    <field name="sichtbarkeit" type="boolean" column="Sichtbarkeit" nullable="false"/>
    <field name="beschreibung" type="string" column="Beschreibung" length="1023" nullable="true">
      <options>
        <option name="fixed"/>
      </options>
    </field>
    <field name="abgabedatum" type="date" column="Abgabedatum" nullable="true"/>
    <field name="erstelldatum" type="date" column="Erstelldatum" nullable="false"/>
    <field name="anmerkung" type="string" column="Anmerkung" length="1023" nullable="true">
      <options>
        <option name="fixed"/>
      </options>
    </field>
  </entity>
</doctrine-mapping>
